yerba/__init__.py
yerba/__main__.py
yerba/defaults.py
yerba/logger_setup.py
yerba/main_rutine.py
yerba/base/__init__.py
yerba/base/box.py
yerba/base/image.py
yerba/base/parser.py
yerba/base/properties.py
yerba/base/slide.py
yerba/base/template.py
yerba/base/template_protocol.py
yerba/base/ytext.py
yerba/managers/__init__.py
yerba/managers/color_manager.py
yerba/managers/id_manager.py
yerba/managers/singleton.py
yerba/templates/__init__.py
yerba/templates/basic.py
yerba/templates/nice.py
yerba/utils/__init__.py
yerba/utils/aux_classes.py
yerba/utils/aux_functions.py
yerba/utils/constants.py
yerba/utils/latex.py
yerba-0.0.3a0.dev2.dist-info/LICENSE
yerba-0.0.3a0.dev2.dist-info/METADATA
yerba-0.0.3a0.dev2.dist-info/WHEEL
yerba-0.0.3a0.dev2.dist-info/entry_points.txt
yerba-0.0.3a0.dev2.dist-info/top_level.txt
yerba-0.0.3a0.dev2.dist-info/RECORD
