Metadata-Version: 2.2
Name: yerba
Version: 0.0.3a0.dev2
Author-email: "Bernardo L. Español" <esp.bernardo@gmail.com>
Requires-Python: >=3.8
License-File: LICENSE
Requires-Dist: manim
Requires-Dist: manim-mobject-svg
Requires-Dist: markdown-it-py
Requires-Dist: mdformat
Requires-Dist: mdit-py-plugins
Requires-Dist: numpy
Requires-Dist: pillow
Requires-Dist: pyyaml
